[
  {
    "Name": "RandomAI",
    "hz_player_name": "RandomAI",
    "player_id": "2954699",
    "portal_id": "5",
    "privacy_flag": "n",
    "ret_msg": null
  },
  {
    "Name": "RandomaiggN",
    "hz_player_name": "RandomaiggN",
    "player_id": "709204158",
    "portal_id": "5",
    "privacy_flag": "n",
    "ret_msg": null
  },
  {
    "Name": "RandomAimXD",
    "hz_player_name": "RandomAimXD",
    "player_id": "708552447",
    "portal_id": "5",
    "privacy_flag": "n",
    "ret_msg": null
  },
  {
    "Name": "Randomain",
    "hz_player_name": "Randomain",
    "player_id": "8326039",
    "portal_id": "5",
    "privacy_flag": "n",
    "ret_msg": null
  },
  {
    "Name": "randomair",
    "hz_player_name": "randomair",
    "player_id": "708788409",
    "portal_id": "22",
    "privacy_flag": "n",
    "ret_msg": null
  },
  {
    "Name": "Randomaizer",
    "hz_player_name": "Randomaizer",
    "player_id": "1247249",
    "portal_id": "1",
    "privacy_flag": "n",
    "ret_msg": null
  },
  {
    "Name": "RandOmaizerX",
    "hz_player_name": "RandOmaizerX",
    "player_id": "11146548",
    "portal_id": "28",
    "privacy_flag": "n",
    "ret_msg": null
  }
]