[
  {
    "Account_Gods_Played": 24,
    "Account_Level": 105,
    "GodId": 3518,
    "GodLevel": 6,
    "GodName": "Baron Samedi",
    "Mastery_Level": 6,
    "Match": 1232931625,
    "Queue": "440",
    "Rank_Stat": 1600,
    "SkinId": 17008,
    "Tier": 1,
    "mapGame": "Joust_1v1",
    "playerCreated": "10/7/2020 8:23:49 AM",
    "playerId": "712895118",
    "playerName": "theejz",
    "playerRegion": "North America West",
    "ret_msg": null,
    "taskForce": 2,
    "tierLosses": 0,
    "tierPoints": 77,
    "tierWins": 0
  },
  {
    "Account_Gods_Played": 115,
    "Account_Level": 160,
    "GodId": 1919,
    "GodLevel": 4,
    "GodName": "Athena",
    "Mastery_Level": 4,
    "Match": 1232931625,
    "Queue": "440",
    "Rank_Stat": 1535.49854,
    "SkinId": 19161,
    "Tier": 13,
    "mapGame": "Joust_1v1",
    "playerCreated": "12/25/2012 6:34:56 PM",
    "playerId": "897514",
    "playerName": "Hatmaster",
    "playerRegion": "North America West",
    "ret_msg": null,
    "taskForce": 1,
    "tierLosses": 0,
    "tierPoints": 0,
    "tierWins": 0
  }
]